EasyJsonDB/easyjsondb.py
EasyJsonDB-0.1.dist-info/LICENSE.txt
EasyJsonDB-0.1.dist-info/METADATA
EasyJsonDB-0.1.dist-info/WHEEL
EasyJsonDB-0.1.dist-info/top_level.txt
EasyJsonDB-0.1.dist-info/RECORD
