Metadata-Version: 2.1
Name: EasyJsonDB
Version: 0.1
Summary: A simple db script for everyone to use it
Home-page: https://github.com/vlnerable/EasyDB
Author: vlnerable
Author-email: vlnerablehacking@gmail.com
License: UNKNOWN
Platform: UNKNOWN
Classifier: Programming Language :: Python :: 3
Classifier: License :: OSI Approved :: MIT License
Classifier: Operating System :: OS Independent
Requires-Python: >=3
